Metadata-Version: 1.0
Name: dpyutils
Version: 0.0.2
Summary: A set of utilities for discord.py
Home-page: https://github.com/KowlinMC/D.PY-utils
Author: Kowlin
Author-email: chromeuser1@outlook.com
License: MIT
Platform: UNKNOWN
